workflow_for_git_huzaifa/__init__.py
workflow_for_git_huzaifa/app.py
workflow_for_git_huzaifa-0.1.0.dist-info/METADATA
workflow_for_git_huzaifa-0.1.0.dist-info/WHEEL
workflow_for_git_huzaifa-0.1.0.dist-info/RECORD
