Metadata-Version: 2.1
Name: workflow-for-git-huzaifa
Version: 0.1.0
Summary: 
Author: Huzaifa Naeem
Author-email: huzaifa.naeem@datumlabs.io
Requires-Python: >=3.12,<4.0
Classifier: Programming Language :: Python :: 3
Classifier: Programming Language :: Python :: 3.12
Classifier: Programming Language :: Python :: 3.13
Requires-Dist: flask (>=3.1.0,<4.0.0)
Requires-Dist: pandas (>=2.2.3,<3.0.0)
